{
  "ABEO": {
    "stage": "BUY1",
    "price": 7.12,
    "time": "2026-07-10T10:32:56.564722+00:00"
  },
  "ARMK": {
    "stage": "BUY1",
    "price": 57.88,
    "time": "2026-07-10T10:32:58.228769+00:00"
  },
  "PBF": {
    "stage": "BUY1",
    "price": 53.31,
    "time": "2026-07-10T10:32:59.895872+00:00"
  },
  "EWTX": {
    "stage": "BUY1",
    "price": 48.35,
    "time": "2026-07-10T10:33:01.596431+00:00"
  },
  "PRVA": {
    "stage": "BUY1",
    "price": 27.77,
    "time": "2026-07-10T10:33:03.290023+00:00"
  },
  "TXG": {
    "stage": "BUY1",
    "price": 43.1,
    "time": "2026-07-10T10:33:04.966286+00:00"
  },
  "DK": {
    "stage": "BUY1",
    "price": 56.09,
    "time": "2026-07-10T10:33:06.637412+00:00"
  },
  "IMVT": {
    "stage": "BUY1",
    "price": 41.09,
    "time": "2026-07-10T10:33:08.280713+00:00"
  },
  "SVC": {
    "stage": "BUY1",
    "price": 8.75,
    "time": "2026-07-10T10:33:09.994044+00:00"
  },
  "DBRG": {
    "stage": "준비",
    "price": 15.75,
    "time": "2026-07-10T10:33:11.692697+00:00"
  },
  "HR": {
    "stage": "준비",
    "price": 20.69,
    "time": "2026-07-10T10:33:13.413725+00:00"
  },
  "ONB": {
    "stage": "준비",
    "price": 26.17,
    "time": "2026-07-10T10:33:15.096929+00:00"
  },
  "PD": {
    "stage": "준비",
    "price": 10.46,
    "time": "2026-07-10T10:33:16.823410+00:00"
  },
  "BBY": {
    "stage": "준비",
    "price": 79.99,
    "time": "2026-07-10T10:33:18.498071+00:00"
  },
  "FIBK": {
    "stage": "준비",
    "price": 38.91,
    "time": "2026-07-10T10:33:20.284075+00:00"
  }
}